debugonce_packages/__init__.py
debugonce_packages/cli.py
debugonce_packages/decorator.py
debugonce_packages/storage.py
debugonce_packages/tracking_context.py
debugonce_packages/utils.py
debugonce-0.6.3.dist-info/LICENSE
debugonce-0.6.3.dist-info/METADATA
debugonce-0.6.3.dist-info/WHEEL
debugonce-0.6.3.dist-info/entry_points.txt
debugonce-0.6.3.dist-info/top_level.txt
debugonce-0.6.3.dist-info/RECORD
