Metadata-Version: 2.1
Name: debugonce
Version: 0.6.3
Summary: Effortlessly capture and reproduce bugs in your python code
Home-page: https://github.com/Sujith-sunny/debugonce
Author: Sujith Joseph
Author-email: nsjr2002@gmail.com
License: MIT
Keywords: debugonce, debugging, bug reproduction, python, error tracking, error reporting,,error handling, bug capture, bug reproduction, python debugging, error reproduction,,error logging, bug tracking, bug reporting, error analysis, debugging tools,,error handling tools, bug capture tools, bug reproduction tools,python error tracking, python error reporting, python error handling,,python bug capture, python bug reproduction, python debugging tools,,python error handling tools, python bug capt
Classifier: Programming Language :: Python :: 3
Classifier: Programming Language :: Python :: 3.8
Classifier: License :: OSI Approved :: MIT License
Classifier: Operating System :: OS Independent
Requires-Python: >=3.8
License-File: LICENSE
Requires-Dist: click
Requires-Dist: psutil
Requires-Dist: requests
